linesample/__init__.py
linesample/__main__.py
linesample-0.1.1.dist-info/LICENSE
linesample-0.1.1.dist-info/METADATA
linesample-0.1.1.dist-info/WHEEL
linesample-0.1.1.dist-info/entry_points.txt
linesample-0.1.1.dist-info/top_level.txt
linesample-0.1.1.dist-info/RECORD
