Metadata-Version: 2.1
Name: linesample
Version: 0.1.1
Summary: Utility to randomly sample lines from a file
Home-page: https://github.com/syclops/linesample
Author: Steve Matsumoto
Author-email: stephanos.matsumoto@sporic.me
License: MIT
Platform: UNKNOWN
Classifier: Development Status :: 3 - Alpha
Classifier: Environment :: Console
Classifier: Intended Audience :: Science/Research
Classifier: License :: OSI Approved :: MIT License
Classifier: Operating System :: OS Independent
Classifier: Programming Language :: Python :: 3
Requires-Python: >=3
